dfnstream_py/__init__.py
dfnstream_py/dfnstream.py
dfnstream_py/dfnstream_onnx.py
dfnstream_py/py.typed
dfnstream_py/lib/libdf_aarch64_linux.so
dfnstream_py/lib/libdf_arm64_darwin.dylib
dfnstream_py/lib/libdf_x86_64_linux.so
dfnstream_py/models/DeepFilterNet2_onnx.tar.gz
dfnstream_py/models/DeepFilterNet2_onnx_ll.tar.gz
dfnstream_py/models/DeepFilterNet3_ll_onnx.tar.gz
dfnstream_py/models/DeepFilterNet3_onnx.tar.gz
dfnstream_py/onnx/denoiser_model.onnx
dfnstream_py/onnx/dfn.py
dfnstream_py-0.2.1.dist-info/METADATA
dfnstream_py-0.2.1.dist-info/WHEEL
dfnstream_py-0.2.1.dist-info/licenses/LICENSE
dfnstream_py-0.2.1.dist-info/RECORD
