Metadata-Version: 2.4
Name: dfnstream-py
Version: 0.2.1
Summary: Real-time audio denoising using DeepFilterNet with streaming
Project-URL: Homepage, https://github.com/outspeed-ai/dfnstream-py
Project-URL: Repository, https://github.com/outspeed-ai/dfnstream-py
Project-URL: Issues, https://github.com/outspeed-ai/dfnstream-py/issues
Author-email: Sayan Jyoti Das <sayanjyotidasworkmail@gmail.com>
License: MIT
License-File: LICENSE
Keywords: audio,deepfilternet,denoising,real-time,streaming
Classifier: Development Status :: 3 - Alpha
Classifier: Intended Audience :: Developers
Classifier: Intended Audience :: Science/Research
Classifier: License :: OSI Approved :: MIT License
Classifier: Operating System :: MacOS :: MacOS X
Classifier: Operating System :: POSIX :: Linux
Classifier: Programming Language :: Python :: 3
Classifier: Programming Language :: Python :: 3.11
Classifier: Programming Language :: Python :: 3.12
Classifier: Topic :: Multimedia :: Sound/Audio
Classifier: Topic :: Multimedia :: Sound/Audio :: Analysis
Classifier: Topic :: Scientific/Engineering :: Artificial Intelligence
Requires-Python: >=3.11
Requires-Dist: numpy<2.3,>=1.24
Requires-Dist: onnxruntime>=1.22.0
